st_infographic_component/__init__.py
st_infographic_component/frontend/build/asset-manifest.json
st_infographic_component/frontend/build/bootstrap.min.css
st_infographic_component/frontend/build/index.html
st_infographic_component/frontend/build/static/css/main.be4a6ff5.css
st_infographic_component/frontend/build/static/css/main.be4a6ff5.css.map
st_infographic_component/frontend/build/static/js/main.e50eb4b6.js
st_infographic_component/frontend/build/static/js/main.e50eb4b6.js.LICENSE.txt
st_infographic_component/frontend/build/static/js/main.e50eb4b6.js.map
st_infoGraphic_component-0.1.1.dist-info/LICENSE
st_infoGraphic_component-0.1.1.dist-info/METADATA
st_infoGraphic_component-0.1.1.dist-info/WHEEL
st_infoGraphic_component-0.1.1.dist-info/top_level.txt
st_infoGraphic_component-0.1.1.dist-info/RECORD
