Metadata-Version: 2.1
Name: st-infoGraphic-component
Version: 0.1.1
Summary: UNKNOWN
Home-page: UNKNOWN
Author: Sam Van Lier
Author-email: sam.vanlier@hotmail.com
License: UNKNOWN
Platform: UNKNOWN
Requires-Python: >=3.6
License-File: LICENSE
Requires-Dist: streamlit (>=0.63)
